README.md
setup.py
image_blobs/__init__.py
image_blobs/util.py
image_blobs.egg-info/PKG-INFO
image_blobs.egg-info/SOURCES.txt
image_blobs.egg-info/dependency_links.txt
image_blobs.egg-info/requires.txt
image_blobs.egg-info/top_level.txt
image_blobs.egg-info/zip-safe
image_blobs/test/__init__.py
image_blobs/test/test_find.py