Metadata-Version: 2.1
Name: image-blobs
Version: 0.1.0
Summary: Analysis for gray scale images containing gaussian shaped blobs
Home-page: https://github.com/mdavidsaver/blobs
Author: Michael Davidsaver
Author-email: mdavidsaver@gmail.com
License: GPL-3+
Keywords: image fitting
Platform: UNKNOWN
Classifier: Programming Language :: Python :: 2.7
Classifier: Programming Language :: Python :: 3
Classifier: License :: OSI Approved :: GNU General Public License v3 or later (GPLv3+)
Classifier: Intended Audience :: Science/Research
Classifier: Topic :: Scientific/Engineering
Classifier: Operating System :: OS Independent
Requires-Python: >=2.7
Provides-Extra: test
